{"timestamp":"2024-07-02T16:01:01Z","id":"39808942130","type":"IssuesEvent","actor":{"id":70667788,"login":"Naomi-Wash","display_login":"Naomi-Wash","gravatar_id":"","url":"https://api.github.com/users/Naomi-Wash","avatar_url":"https://avatars.githubusercontent.com/u/70667788?"},"actor_id":{"id":70667788,"login":"Naomi-Wash","display_login":"Naomi-Wash","gravatar_id":"","url":"https://api.github.com/users/Naomi-Wash","avatar_url":"https://avatars.githubusercontent.com/u/70667788?"},"action":"closed","repo":"PQCA/TAC"}
{"timestamp":"2024-07-02T16:01:02Z","id":"39808942781","type":"IssueCommentEvent","actor":{"id":70667788,"login":"Naomi-Wash","display_login":"Naomi-Wash","gravatar_id":"","url":"https://api.github.com/users/Naomi-Wash","avatar_url":"https://avatars.githubusercontent.com/u/70667788?"},"actor_id":{"id":70667788,"login":"Naomi-Wash","display_login":"Naomi-Wash","gravatar_id":"","url":"https://api.github.com/users/Naomi-Wash","avatar_url":"https://avatars.githubusercontent.com/u/70667788?"},"action":"created","repo":"PQCA/TAC"}
{"timestamp":"2024-07-02T16:03:16Z","id":"39809014134","type":"PullRequestEvent","actor":{"id":466142,"login":"ryjones","display_login":"ryjones","gravatar_id":"","url":"https://api.github.com/users/ryjones","avatar_url":"https://avatars.githubusercontent.com/u/466142?"},"actor_id":{"id":466142,"login":"ryjones","display_login":"ryjones","gravatar_id":"","url":"https://api.github.com/users/ryjones","avatar_url":"https://avatars.githubusercontent.com/u/466142?"},"action":"closed","repo":"PQCA/TAC"}
{"timestamp":"2024-07-02T16:03:16Z","id":"39809014342","type":"PushEvent","actor":{"id":466142,"login":"ryjones","display_login":"ryjones","gravatar_id":"","url":"https://api.github.com/users/ryjones","avatar_url":"https://avatars.githubusercontent.com/u/466142?"},"actor_id":{"id":466142,"login":"ryjones","display_login":"ryjones","gravatar_id":"","url":"https://api.github.com/users/ryjones","avatar_url":"https://avatars.githubusercontent.com/u/466142?"},"action":null,"repo":"PQCA/TAC"}
{"timestamp":"2024-07-02T16:03:16Z","id":"39809014506","type":"DeleteEvent","actor":{"id":466142,"login":"ryjones","display_login":"ryjones","gravatar_id":"","url":"https://api.github.com/users/ryjones","avatar_url":"https://avatars.githubusercontent.com/u/466142?"},"actor_id":{"id":466142,"login":"ryjones","display_login":"ryjones","gravatar_id":"","url":"https://api.github.com/users/ryjones","avatar_url":"https://avatars.githubusercontent.com/u/466142?"},"action":null,"repo":"PQCA/TAC"}
{"timestamp":"2024-07-02T16:10:06Z","id":"39809226103","type":"PushEvent","actor":{"id":70667788,"login":"Naomi-Wash","display_login":"Naomi-Wash","gravatar_id":"","url":"https://api.github.com/users/Naomi-Wash","avatar_url":"https://avatars.githubusercontent.com/u/70667788?"},"actor_id":{"id":70667788,"login":"Naomi-Wash","display_login":"Naomi-Wash","gravatar_id":"","url":"https://api.github.com/users/Naomi-Wash","avatar_url":"https://avatars.githubusercontent.com/u/70667788?"},"action":null,"repo":"PQCA/TAC"}
